ctrlp/__init__.py
ctrlp/comm_handler.py
ctrlp/config_handler.py
ctrlp/get_files.py
ctrlp/helper_utils.py
ctrlp/validate_commands.py
ctrlp/command_spec/__init__.py
ctrlp/command_spec/commands_2.0.yaml
ctrlp/command_spec/commands_2.1.yaml
ctrlp/command_spec/commands_2.2.yaml
ctrlp/command_spec/commands_2.3.yaml
ctrlp/command_spec/commands_2.4.yaml
ctrlp/command_spec/commands_2.5.yaml
ctrlp-1.0.5.dist-info/LICENSE
ctrlp-1.0.5.dist-info/METADATA
ctrlp-1.0.5.dist-info/WHEEL
ctrlp-1.0.5.dist-info/top_level.txt
ctrlp-1.0.5.dist-info/RECORD
