Metadata-Version: 2.1
Name: ctrlp
Version: 1.0.5
Summary: Low-level hardware interface for Ctrl-P pressure control systems.
Home-page: https://github.com/cbteeple/ctrlp
Author: Clark Teeple
Author-email: cbteeple@gmail.com
License: MIT
Platform: UNKNOWN
Classifier: Development Status :: 5 - Production/Stable
Classifier: Intended Audience :: Developers
Classifier: Topic :: System :: Hardware :: Hardware Drivers
Classifier: License :: OSI Approved :: MIT License
Classifier: Operating System :: OS Independent
Classifier: Programming Language :: Python :: 3
Requires-Dist: numpy
Requires-Dist: scipy
Requires-Dist: matplotlib
Requires-Dist: seaborn
Requires-Dist: PyYAML
Requires-Dist: pyserial
